Metadata-Version: 1.1
Name: dict-obj
Version: 0.0.1
Summary: Object interface for a Python dictionary.
Home-page: https://github.com/jfjlaros/dict-obj
Author: Jeroen F.J. Laros
Author-email: jlaros@fixedpoint.nl
License: MIT
Platform: UNKNOWN
Classifier: Programming Language :: Python :: 3
Classifier: Programming Language :: Python :: 3.5
